CHANGELOG.rst
MANIFEST.in
README.rst
setup.py
sphinxcontrib/__init__.py
sphinxcontrib/excel_table_plus/__init__.py
sphinxcontrib/excel_table_plus/excel_table.py
sphinxcontrib/excel_table_plus/resources/_static/handsontable.full.min.css
sphinxcontrib/excel_table_plus/resources/_static/handsontable.full.min.js
sphinxcontrib/excel_table_plus/resources/_templates/layout.html
sphinxcontrib/excel_table_plus/templates/table.html
sphinxcontrib_excel_table_plus.egg-info/PKG-INFO
sphinxcontrib_excel_table_plus.egg-info/SOURCES.txt
sphinxcontrib_excel_table_plus.egg-info/dependency_links.txt
sphinxcontrib_excel_table_plus.egg-info/not-zip-safe
sphinxcontrib_excel_table_plus.egg-info/requires.txt
sphinxcontrib_excel_table_plus.egg-info/top_level.txt