Metadata-Version: 1.1
Name: sphinxcontrib-excel-table-plus
Version: 1.0.8.2
Summary: Embed excel file as an excel-alike table into sphinx documentation. Forked with extended support for html in columns.
Home-page: https://github.com/emerge-ehri/sphinxcontrib-excel-table-plus
Author: Larry Babb
Author-email: larry.babb@gmail.com
License: Apache License
Download-URL: https://github.com/emerge-ehri/sphinxcontrib-excel-table-plus/archive/1.0.8.2.tar.gz
Keywords: python,sphinx,excel
Platform: UNKNOWN
Classifier: Topic :: Office/Business
Classifier: Topic :: Utilities
Classifier: Topic :: Software Development :: Libraries
Classifier: Programming Language :: Python
Classifier: Intended Audience :: Developers
Classifier: Programming Language :: Python :: 2.6
Classifier: Programming Language :: Python :: 2.7
Classifier: Programming Language :: Python :: 3.3
Classifier: Programming Language :: Python :: 3.4
Classifier: Programming Language :: Python :: 3.5
Classifier: Programming Language :: Python :: 3.6
Classifier: License :: OSI Approved :: Apache Software License
